LICENSE
README.md
setup.py
Library/__init__.py
Library/seqs.py
Protein_L_YnBn.egg-info/PKG-INFO
Protein_L_YnBn.egg-info/SOURCES.txt
Protein_L_YnBn.egg-info/dependency_links.txt
Protein_L_YnBn.egg-info/requires.txt
Protein_L_YnBn.egg-info/top_level.txt
tests/__init__.py